examples/__init__.py
examples/sfr/__init__.py
examples/sfr/run.py
examples/sfr/sfr_breed.py
examples/sfr/sfr_model.py
examples/sfr/step_func_code.py
examples/sir/__init__.py
examples/sir/run.py
examples/sir/sir_breed.py
examples/sir/sir_model.py
examples/sir/sir_step_func.py
examples/sir/state.py
examples/sir/step_func_code.py
examples/sir/test_args.py
examples/sir/test_perf.py
examples/sir/tutorial_run.py
sagesim/__init__.py
sagesim/agent.py
sagesim/breed.py
sagesim/internal_utils.py
sagesim/model.py
sagesim/space.py
sagesim/utils.py
sagesim-0.3.0.dist-info/licenses/LICENSE
sagesim-0.3.0.dist-info/METADATA
sagesim-0.3.0.dist-info/WHEEL
sagesim-0.3.0.dist-info/top_level.txt
sagesim-0.3.0.dist-info/RECORD
