Metadata-Version: 2.4
Name: sagesim
Version: 0.3.0
Summary: Scalable Agent-based GPU Enabled Simulator.
Author-email: Chathika Gunaratne <chathikagunaratne@gmail.com>, Xi Zhang <cc.zhang1992@gmail.com>
Maintainer-email: Chathika Gunaratne <chathikagunaratne@gmail.com>, Xi Zhang <cc.zhang1992@gmail.com>
License: MIT License
Project-URL: Repository, https://github.com/ornl/sagesim.git
Keywords: agent-based,hpc,gpu
Requires-Python: >=3.11
License-File: LICENSE
Requires-Dist: awkward==2.7.4
Requires-Dist: networkx==3.4.2
Requires-Dist: numpy==2.2.3
Requires-Dist: ragged==0.2.0
Dynamic: license-file
